{
    "swagger": "2.0",
    "info": {
        "description": "Alerting service API documentation",
        "title": "Alerting Service API",
        "contact": {
            "name": "API Support",
            "url": "http://www.swagger.io/support",
            "email": "support@swagger.io"
        },
        "license": {
            "name": "Apache 2.0",
            "url": "http://www.apache.org/licenses/LICENSE-2.0.html"
        },
        "version": "1.0"
    },
    "host": "localhost:8010",
    "basePath": "/alerting",
    "paths": {
        "/alerting/receiver": {
            "get": {
                "description": "根据接收者ID获取单个通知接收者的详细信息",
                "consumes": [
                    "application/json"
                ],
                "produces": [
                    "application/json"
                ],
                "tags": [
                    "接收者管理"
                ],
                "summary": "获取单个接收者详情",
                "parameters": [
                    {
                        "type": "string",
                        "description": "接收者ID",
                        "name": "id",
                        "in": "query",
                        "required": true
                    }
                ],
                "responses": {
                    "200": {
                        "description": "查询成功",
                        "schema": {
                            "allOf": [
                                {
                                    "$ref": "#/definitions/errno.Result"
                                },
                                {
                                    "type": "object",
                                    "properties": {
                                        "data": {
                                            "$ref": "#/definitions/alerting.Receiver"
                                        }
                                    }
                                }
                            ]
                        }
                    },
                    "400": {
                        "description": "参数错误",
                        "schema": {
                            "$ref": "#/definitions/errno.Result"
                        }
                    },
                    "500": {
                        "description": "服务器内部错误",
                        "schema": {
                            "$ref": "#/definitions/errno.Result"
                        }
                    }
                }
            },
            "put": {
                "description": "更新指定ID的通知接收者信息",
                "consumes": [
                    "application/json"
                ],
                "produces": [
                    "application/json"
                ],
                "tags": [
                    "接收者管理"
                ],
                "summary": "更新通知接收者",
                "parameters": [
                    {
                        "description": "更新接收者请求参数",
                        "name": "request",
                        "in": "body",
                        "required": true,
                        "schema": {
                            "$ref": "#/definitions/alerting.UpdateReceiverRequest"
                        }
                    }
                ],
                "responses": {
                    "200": {
                        "description": "更新成功",
                        "schema": {
                            "allOf": [
                                {
                                    "$ref": "#/definitions/errno.Result"
                                },
                                {
                                    "type": "object",
                                    "properties": {
                                        "data": {
                                            "$ref": "#/definitions/alerting.IDResponse"
                                        }
                                    }
                                }
                            ]
                        }
                    },
                    "400": {
                        "description": "参数错误",
                        "schema": {
                            "$ref": "#/definitions/errno.Result"
                        }
                    },
                    "409": {
                        "description": "接收者已存在",
                        "schema": {
                            "$ref": "#/definitions/errno.Result"
                        }
                    },
                    "500": {
                        "description": "服务器内部错误",
                        "schema": {
                            "$ref": "#/definitions/errno.Result"
                        }
                    }
                }
            },
            "post": {
                "description": "创建一个新的通知接收者，用于接收告警通知",
                "consumes": [
                    "application/json"
                ],
                "produces": [
                    "application/json"
                ],
                "tags": [
                    "接收者管理"
                ],
                "summary": "创建通知接收者",
                "parameters": [
                    {
                        "description": "创建接收者请求参数",
                        "name": "request",
                        "in": "body",
                        "required": true,
                        "schema": {
                            "$ref": "#/definitions/alerting.CreateReceiverRequest"
                        }
                    }
                ],
                "responses": {
                    "200": {
                        "description": "创建成功",
                        "schema": {
                            "allOf": [
                                {
                                    "$ref": "#/definitions/errno.Result"
                                },
                                {
                                    "type": "object",
                                    "properties": {
                                        "data": {
                                            "$ref": "#/definitions/alerting.IDResponse"
                                        }
                                    }
                                }
                            ]
                        }
                    },
                    "400": {
                        "description": "参数错误",
                        "schema": {
                            "$ref": "#/definitions/errno.Result"
                        }
                    },
                    "409": {
                        "description": "接收者已存在",
                        "schema": {
                            "$ref": "#/definitions/errno.Result"
                        }
                    },
                    "500": {
                        "description": "服务器内部错误",
                        "schema": {
                            "$ref": "#/definitions/errno.Result"
                        }
                    }
                }
            },
            "delete": {
                "description": "删除指定ID的通知接收者，并更新相关告警规则",
                "consumes": [
                    "application/json"
                ],
                "produces": [
                    "application/json"
                ],
                "tags": [
                    "接收者管理"
                ],
                "summary": "删除通知接收者",
                "parameters": [
                    {
                        "description": "删除接收者请求参数",
                        "name": "request",
                        "in": "body",
                        "required": true,
                        "schema": {
                            "$ref": "#/definitions/alerting.DeleteReceiverRequest"
                        }
                    }
                ],
                "responses": {
                    "200": {
                        "description": "删除成功",
                        "schema": {
                            "$ref": "#/definitions/errno.Result"
                        }
                    },
                    "400": {
                        "description": "参数错误",
                        "schema": {
                            "$ref": "#/definitions/errno.Result"
                        }
                    },
                    "500": {
                        "description": "服务器内部错误",
                        "schema": {
                            "$ref": "#/definitions/errno.Result"
                        }
                    }
                }
            }
        },
        "/alerting/receiver/default_notify_types/list": {
            "post": {
                "description": "获取系统支持的通知类型列表",
                "consumes": [
                    "application/json"
                ],
                "produces": [
                    "application/json"
                ],
                "tags": [
                    "接收者管理"
                ],
                "summary": "获取默认通知类型",
                "responses": {
                    "200": {
                        "description": "查询成功",
                        "schema": {
                            "allOf": [
                                {
                                    "$ref": "#/definitions/errno.Result"
                                },
                                {
                                    "type": "object",
                                    "properties": {
                                        "data": {
                                            "$ref": "#/definitions/alerting.ListDefaultNotifyTypesResponse"
                                        }
                                    }
                                }
                            ]
                        }
                    },
                    "500": {
                        "description": "服务器内部错误",
                        "schema": {
                            "$ref": "#/definitions/errno.Result"
                        }
                    }
                }
            }
        },
        "/alerting/receiver/list": {
            "post": {
                "description": "根据过滤条件分页获取通知接收者列表",
                "consumes": [
                    "application/json"
                ],
                "produces": [
                    "application/json"
                ],
                "tags": [
                    "接收者管理"
                ],
                "summary": "获取接收者列表",
                "parameters": [
                    {
                        "description": "列表查询请求参数",
                        "name": "request",
                        "in": "body",
                        "required": true,
                        "schema": {
                            "$ref": "#/definitions/alerting.ListReceiverRequest"
                        }
                    }
                ],
                "responses": {
                    "200": {
                        "description": "查询成功",
                        "schema": {
                            "allOf": [
                                {
                                    "$ref": "#/definitions/errno.Result"
                                },
                                {
                                    "type": "object",
                                    "properties": {
                                        "data": {
                                            "$ref": "#/definitions/alerting.ListReceiverResponse"
                                        }
                                    }
                                }
                            ]
                        }
                    },
                    "400": {
                        "description": "参数错误",
                        "schema": {
                            "$ref": "#/definitions/errno.Result"
                        }
                    },
                    "500": {
                        "description": "服务器内部错误",
                        "schema": {
                            "$ref": "#/definitions/errno.Result"
                        }
                    }
                }
            }
        },
        "/alerting/receiver/multi": {
            "post": {
                "description": "根据多个接收者ID批量获取通知接收者的详细信息",
                "consumes": [
                    "application/json"
                ],
                "produces": [
                    "application/json"
                ],
                "tags": [
                    "接收者管理"
                ],
                "summary": "批量获取接收者详情",
                "parameters": [
                    {
                        "description": "批量查询请求参数",
                        "name": "request",
                        "in": "body",
                        "required": true,
                        "schema": {
                            "$ref": "#/definitions/alerting.ListMultiReceiversRequest"
                        }
                    }
                ],
                "responses": {
                    "200": {
                        "description": "查询成功",
                        "schema": {
                            "allOf": [
                                {
                                    "$ref": "#/definitions/errno.Result"
                                },
                                {
                                    "type": "object",
                                    "properties": {
                                        "data": {
                                            "$ref": "#/definitions/alerting.ListMultiReceiversResponse"
                                        }
                                    }
                                }
                            ]
                        }
                    },
                    "400": {
                        "description": "参数错误",
                        "schema": {
                            "$ref": "#/definitions/errno.Result"
                        }
                    },
                    "500": {
                        "description": "服务器内部错误",
                        "schema": {
                            "$ref": "#/definitions/errno.Result"
                        }
                    }
                }
            }
        },
        "/alerting/receiver/wecom/notify": {
            "post": {
                "description": "通过企业微信机器人发送通知消息",
                "consumes": [
                    "application/json"
                ],
                "produces": [
                    "application/json"
                ],
                "tags": [
                    "接收者管理"
                ],
                "summary": "发送企业微信通知",
                "parameters": [
                    {
                        "description": "企业微信通知请求参数",
                        "name": "request",
                        "in": "body",
                        "required": true,
                        "schema": {
                            "$ref": "#/definitions/alerting.CreateWecomNotifyRequest"
                        }
                    }
                ],
                "responses": {
                    "200": {
                        "description": "发送成功",
                        "schema": {
                            "allOf": [
                                {
                                    "$ref": "#/definitions/errno.Result"
                                },
                                {
                                    "type": "object",
                                    "properties": {
                                        "data": {
                                            "$ref": "#/definitions/alerting.CreateWecomNotifyResponse"
                                        }
                                    }
                                }
                            ]
                        }
                    },
                    "400": {
                        "description": "参数错误",
                        "schema": {
                            "$ref": "#/definitions/errno.Result"
                        }
                    },
                    "500": {
                        "description": "服务器内部错误",
                        "schema": {
                            "$ref": "#/definitions/errno.Result"
                        }
                    }
                }
            }
        },
        "/alerting/workspace/alert/default_info/list": {
            "post": {
                "security": [
                    {
                        "ApiKeyAuth": []
                    }
                ],
                "description": "returns the list of alerts default infos",
                "consumes": [
                    "application/json"
                ],
                "produces": [
                    "application/json"
                ],
                "tags": [
                    "alert"
                ],
                "parameters": [
                    {
                        "type": "string",
                        "description": "account token",
                        "name": "access-token",
                        "in": "header"
                    },
                    {
                        "type": "string",
                        "description": "unique id of account",
                        "name": "uid",
                        "in": "header"
                    },
                    {
                        "description": "json format",
                        "name": "data",
                        "in": "body",
                        "required": true,
                        "schema": {
                            "$ref": "#/definitions/alerting-service_internal_service.ListAlertDefaultInfoRequest"
                        }
                    }
                ],
                "responses": {
                    "200": {
                        "description": "ok",
                        "schema": {
                            "allOf": [
                                {
                                    "$ref": "#/definitions/errno.Result"
                                },
                                {
                                    "type": "object",
                                    "properties": {
                                        "data": {
                                            "$ref": "#/definitions/alerting-service_internal_service.ListAlertDefaultInfoResponse"
                                        }
                                    }
                                }
                            ]
                        }
                    }
                }
            }
        },
        "/alerting/workspace/alert/rule/create": {
            "post": {
                "security": [
                    {
                        "ApiKeyAuth": []
                    }
                ],
                "description": "create an alert",
                "consumes": [
                    "application/json"
                ],
                "produces": [
                    "application/json"
                ],
                "tags": [
                    "alert"
                ],
                "parameters": [
                    {
                        "type": "string",
                        "description": "account token",
                        "name": "access-token",
                        "in": "header"
                    },
                    {
                        "type": "string",
                        "description": "unique id of account",
                        "name": "uid",
                        "in": "header"
                    },
                    {
                        "description": "json format",
                        "name": "data",
                        "in": "body",
                        "required": true,
                        "schema": {
                            "$ref": "#/definitions/biz.CreateAlertRequest"
                        }
                    }
                ],
                "responses": {
                    "200": {
                        "description": "ok",
                        "schema": {
                            "allOf": [
                                {
                                    "$ref": "#/definitions/errno.Result"
                                },
                                {
                                    "type": "object",
                                    "properties": {
                                        "data": {
                                            "$ref": "#/definitions/biz.CreateAlertResponse"
                                        }
                                    }
                                }
                            ]
                        }
                    }
                }
            }
        },
        "/alerting/workspace/alert/rule/delete": {
            "post": {
                "security": [
                    {
                        "ApiKeyAuth": []
                    }
                ],
                "description": "delete an alert",
                "consumes": [
                    "application/json"
                ],
                "produces": [
                    "application/json"
                ],
                "tags": [
                    "alert"
                ],
                "parameters": [
                    {
                        "type": "string",
                        "description": "account token",
                        "name": "access-token",
                        "in": "header"
                    },
                    {
                        "type": "string",
                        "description": "unique id of account",
                        "name": "uid",
                        "in": "header"
                    },
                    {
                        "description": "json format",
                        "name": "data",
                        "in": "body",
                        "required": true,
                        "schema": {
                            "$ref": "#/definitions/biz.DeleteAlertRequest"
                        }
                    }
                ],
                "responses": {
                    "200": {
                        "description": "ok",
                        "schema": {
                            "$ref": "#/definitions/errno.Result"
                        }
                    }
                }
            }
        },
        "/alerting/workspace/alert/rule/list": {
            "post": {
                "security": [
                    {
                        "ApiKeyAuth": []
                    }
                ],
                "description": "returns the list of alerts",
                "consumes": [
                    "application/json"
                ],
                "produces": [
                    "application/json"
                ],
                "tags": [
                    "alert"
                ],
                "parameters": [
                    {
                        "type": "string",
                        "description": "account token",
                        "name": "access-token",
                        "in": "header"
                    },
                    {
                        "type": "string",
                        "description": "unique id of account",
                        "name": "uid",
                        "in": "header"
                    },
                    {
                        "description": "json format",
                        "name": "data",
                        "in": "body",
                        "required": true,
                        "schema": {
                            "$ref": "#/definitions/biz.ListAlertRequest"
                        }
                    }
                ],
                "responses": {
                    "200": {
                        "description": "ok",
                        "schema": {
                            "allOf": [
                                {
                                    "$ref": "#/definitions/errno.Result"
                                },
                                {
                                    "type": "object",
                                    "properties": {
                                        "data": {
                                            "$ref": "#/definitions/biz.ListAlertResponse"
                                        }
                                    }
                                }
                            ]
                        }
                    }
                }
            }
        },
        "/alerting/workspace/alert/rule/update": {
            "post": {
                "security": [
                    {
                        "ApiKeyAuth": []
                    }
                ],
                "description": "update an alert",
                "consumes": [
                    "application/json"
                ],
                "produces": [
                    "application/json"
                ],
                "tags": [
                    "alert"
                ],
                "parameters": [
                    {
                        "type": "string",
                        "description": "account token",
                        "name": "access-token",
                        "in": "header"
                    },
                    {
                        "type": "string",
                        "description": "unique id of account",
                        "name": "uid",
                        "in": "header"
                    },
                    {
                        "description": "json format",
                        "name": "data",
                        "in": "body",
                        "required": true,
                        "schema": {
                            "$ref": "#/definitions/biz.UpdateAlertRequest"
                        }
                    }
                ],
                "responses": {
                    "200": {
                        "description": "ok",
                        "schema": {
                            "allOf": [
                                {
                                    "$ref": "#/definitions/errno.Result"
                                },
                                {
                                    "type": "object",
                                    "properties": {
                                        "data": {
                                            "$ref": "#/definitions/biz.UpdateAlertResponse"
                                        }
                                    }
                                }
                            ]
                        }
                    }
                }
            }
        }
    },
    "definitions": {
        "alerting-service_internal_service.ListAlertDefaultInfoRequest": {
            "type": "object"
        },
        "alerting-service_internal_service.ListAlertDefaultInfoResponse": {
            "type": "object",
            "properties": {
                "alert_default_infos": {
                    "type": "array",
                    "items": {
                        "$ref": "#/definitions/biz.AlertDefaultInfo"
                    }
                }
            }
        },
        "alerting.CreateReceiverRequest": {
            "type": "object",
            "required": [
                "group_id",
                "name",
                "notify_type",
                "status"
            ],
            "properties": {
                "comment": {
                    "type": "string"
                },
                "email": {
                    "type": "string"
                },
                "group_id": {
                    "description": "GroupID 应该为 org_id 或 workspace_id",
                    "type": "string",
                    "minLength": 1
                },
                "name": {
                    "type": "string",
                    "minLength": 1
                },
                "notify_type": {
                    "description": "通知类型：0-邮件，1-短信，2-语音，3-企业微信",
                    "type": "integer",
                    "enum": [
                        0,
                        1,
                        2,
                        3
                    ]
                },
                "phone": {
                    "type": "string"
                },
                "status": {
                    "description": "状态：0-禁用，1-启用",
                    "type": "integer",
                    "enum": [
                        0,
                        1
                    ]
                },
                "wecom_key": {
                    "type": "string"
                }
            }
        },
        "alerting.CreateWecomNotifyRequest": {
            "type": "object",
            "properties": {
                "bottoken": {
                    "type": "string"
                },
                "notify_content": {
                    "type": "string"
                }
            }
        },
        "alerting.CreateWecomNotifyResponse": {
            "type": "object",
            "properties": {
                "notify_result": {
                    "type": "array",
                    "items": {
                        "type": "string"
                    }
                }
            }
        },
        "alerting.DeleteReceiverRequest": {
            "type": "object",
            "required": [
                "id"
            ],
            "properties": {
                "id": {
                    "type": "string",
                    "minLength": 1
                }
            }
        },
        "alerting.IDResponse": {
            "type": "object",
            "properties": {
                "id": {
                    "type": "string"
                }
            }
        },
        "alerting.ListDefaultNotifyTypesResponse": {
            "type": "object",
            "properties": {
                "notify_types": {
                    "type": "array",
                    "items": {
                        "type": "integer"
                    }
                }
            }
        },
        "alerting.ListMultiReceiversRequest": {
            "type": "object",
            "required": [
                "ids"
            ],
            "properties": {
                "ids": {
                    "type": "array",
                    "minItems": 1,
                    "items": {
                        "type": "string"
                    }
                }
            }
        },
        "alerting.ListMultiReceiversResponse": {
            "type": "object",
            "properties": {
                "receivers": {
                    "type": "array",
                    "items": {
                        "$ref": "#/definitions/alerting.Receiver"
                    }
                }
            }
        },
        "alerting.ListReceiverRequest": {
            "type": "object",
            "required": [
                "page",
                "page_size"
            ],
            "properties": {
                "page": {
                    "type": "integer",
                    "minimum": 1
                },
                "page_size": {
                    "type": "integer",
                    "minimum": 1
                },
                "receiver_filter": {
                    "$ref": "#/definitions/alerting.ReceiverFilter"
                }
            }
        },
        "alerting.ListReceiverResponse": {
            "type": "object",
            "properties": {
                "receivers": {
                    "type": "array",
                    "items": {
                        "$ref": "#/definitions/alerting.Receiver"
                    }
                },
                "total": {
                    "type": "integer"
                }
            }
        },
        "alerting.Receiver": {
            "type": "object",
            "properties": {
                "comment": {
                    "type": "string"
                },
                "created_at": {
                    "type": "integer"
                },
                "email": {
                    "type": "string"
                },
                "id": {
                    "type": "string"
                },
                "name": {
                    "type": "string"
                },
                "notify_type": {
                    "type": "integer"
                },
                "org_id": {
                    "type": "string"
                },
                "phone": {
                    "type": "string"
                },
                "status": {
                    "type": "integer"
                },
                "updated_at": {
                    "type": "integer"
                },
                "wecom_key": {
                    "type": "string"
                },
                "workspace_id": {
                    "type": "string"
                }
            }
        },
        "alerting.ReceiverFilter": {
            "type": "object",
            "properties": {
                "create_time_order": {
                    "type": "string"
                },
                "email_keyword": {
                    "type": "string"
                },
                "group_ids": {
                    "type": "array",
                    "items": {
                        "type": "string"
                    }
                },
                "ids": {
                    "description": "GroupIDs 应该为 org_id 或 workspace_id array",
                    "type": "array",
                    "items": {
                        "type": "string"
                    }
                },
                "name_keyword": {
                    "type": "string"
                },
                "notify_types": {
                    "type": "array",
                    "items": {
                        "type": "integer"
                    }
                },
                "phone_keyword": {
                    "type": "string"
                },
                "search_keyword": {
                    "type": "string"
                },
                "statuses": {
                    "type": "array",
                    "items": {
                        "type": "integer"
                    }
                },
                "update_time_order": {
                    "type": "string"
                }
            }
        },
        "alerting.UpdateReceiverRequest": {
            "type": "object",
            "required": [
                "id"
            ],
            "properties": {
                "comment": {
                    "type": "string"
                },
                "email": {
                    "type": "string"
                },
                "id": {
                    "type": "string",
                    "minLength": 1
                },
                "name": {
                    "type": "string"
                },
                "notify_type": {
                    "description": "通知类型：0-邮件，1-短信，2-语音，3-企业微信",
                    "type": "integer",
                    "enum": [
                        0,
                        1,
                        2,
                        3
                    ]
                },
                "phone": {
                    "type": "string"
                },
                "status": {
                    "type": "integer",
                    "enum": [
                        0,
                        1
                    ]
                },
                "wecom_key": {
                    "type": "string"
                }
            }
        },
        "biz.Alert": {
            "type": "object",
            "properties": {
                "alert_config": {
                    "$ref": "#/definitions/biz.AlertDefaultInfo"
                },
                "alert_id": {
                    "type": "string"
                },
                "complete_expr": {
                    "type": "string"
                },
                "complete_expr_cn": {
                    "type": "string"
                },
                "created_at": {
                    "type": "string"
                },
                "has_new": {
                    "type": "boolean"
                },
                "org_id": {
                    "description": "if in workspace mode, OrgID is empty",
                    "type": "string"
                },
                "silence_rule": {
                    "$ref": "#/definitions/biz.SilenceRule"
                },
                "state": {
                    "type": "string"
                },
                "updated_at": {
                    "type": "string"
                },
                "workspace_id": {
                    "description": "if in org mode, WorkspaceID is empty",
                    "type": "string"
                }
            }
        },
        "biz.AlertContact": {
            "type": "object",
            "properties": {
                "comment": {
                    "type": "string"
                },
                "email": {
                    "type": "string"
                },
                "id": {
                    "type": "string"
                },
                "name": {
                    "type": "string"
                },
                "org_id": {
                    "type": "string"
                },
                "sms": {
                    "type": "string"
                },
                "state": {
                    "type": "string"
                },
                "tel": {
                    "type": "string"
                },
                "workspace_id": {
                    "type": "string"
                }
            }
        },
        "biz.AlertDefaultInfo": {
            "type": "object",
            "properties": {
                "alert_type": {
                    "type": "string"
                },
                "args": {
                    "type": "array",
                    "items": {
                        "$ref": "#/definitions/biz.ArgsUnit"
                    }
                },
                "category": {
                    "type": "integer"
                },
                "content": {
                    "type": "string"
                },
                "content_cn": {
                    "type": "string"
                },
                "expression": {
                    "type": "string"
                },
                "expression_cn": {
                    "type": "string"
                },
                "expression_id": {
                    "type": "string"
                },
                "id": {
                    "type": "string"
                },
                "is_default_enable": {
                    "type": "boolean"
                },
                "level": {
                    "type": "string"
                },
                "notification": {
                    "$ref": "#/definitions/biz.NotificationInfo"
                }
            }
        },
        "biz.AlertInterval": {
            "type": "object",
            "properties": {
                "unit": {
                    "type": "string"
                },
                "value": {
                    "type": "integer"
                }
            }
        },
        "biz.ArgsUnit": {
            "type": "object",
            "properties": {
                "constraints": {
                    "$ref": "#/definitions/biz.Constraints"
                },
                "key": {
                    "type": "string"
                },
                "value": {
                    "type": "string"
                }
            }
        },
        "biz.Constraints": {
            "type": "object",
            "properties": {
                "is_left_interval_closed": {
                    "type": "boolean"
                },
                "is_right_interval_closed": {
                    "type": "boolean"
                },
                "max": {
                    "type": "string"
                },
                "min": {
                    "type": "string"
                }
            }
        },
        "biz.CreateAlertRequest": {
            "type": "object",
            "properties": {
                "args": {
                    "type": "array",
                    "items": {
                        "$ref": "#/definitions/biz.ArgsUnit"
                    }
                },
                "category": {
                    "description": "metric or event",
                    "type": "integer"
                },
                "expression_id": {
                    "type": "string"
                },
                "level": {
                    "type": "string"
                },
                "receivers": {
                    "type": "array",
                    "items": {
                        "type": "string"
                    }
                },
                "repeat_interval": {
                    "type": "integer"
                },
                "silence_rule": {
                    "$ref": "#/definitions/biz.SilenceRule"
                },
                "workspace_id": {
                    "description": "if in workspace mode, workspace_id is required",
                    "type": "string"
                }
            }
        },
        "biz.CreateAlertResponse": {
            "type": "object",
            "properties": {
                "alert_id": {
                    "type": "string"
                }
            }
        },
        "biz.DeleteAlertRequest": {
            "type": "object",
            "properties": {
                "alert_id": {
                    "type": "string"
                }
            }
        },
        "biz.ListAlertFilter": {
            "type": "object",
            "properties": {
                "alert_types": {
                    "type": "array",
                    "items": {
                        "type": "string"
                    }
                },
                "contact_id": {
                    "type": "string"
                },
                "enable": {
                    "type": "array",
                    "items": {
                        "type": "boolean"
                    }
                },
                "expression": {
                    "type": "string"
                },
                "intervals": {
                    "type": "array",
                    "items": {
                        "$ref": "#/definitions/biz.AlertInterval"
                    }
                },
                "levels": {
                    "type": "array",
                    "items": {
                        "type": "string"
                    }
                },
                "notify_types": {
                    "type": "array",
                    "items": {
                        "type": "string"
                    }
                },
                "org_id": {
                    "type": "string"
                },
                "org_id_list": {
                    "type": "array",
                    "items": {
                        "type": "string"
                    }
                },
                "rule_id": {
                    "type": "string"
                },
                "states": {
                    "type": "array",
                    "items": {
                        "type": "string"
                    }
                },
                "workspace_id": {
                    "type": "string"
                }
            }
        },
        "biz.ListAlertRequest": {
            "type": "object",
            "properties": {
                "filters": {
                    "$ref": "#/definitions/biz.ListAlertFilter"
                },
                "limit": {
                    "type": "integer"
                },
                "offset": {
                    "type": "integer"
                },
                "sorter": {
                    "$ref": "#/definitions/biz.ListAlertSorter"
                }
            }
        },
        "biz.ListAlertResponse": {
            "type": "object",
            "properties": {
                "alerts": {
                    "type": "array",
                    "items": {
                        "$ref": "#/definitions/biz.Alert"
                    }
                },
                "total": {
                    "type": "integer"
                }
            }
        },
        "biz.ListAlertSorter": {
            "type": "object",
            "properties": {
                "is_desc": {
                    "type": "boolean"
                },
                "sort_by": {
                    "type": "string"
                }
            }
        },
        "biz.NotificationInfo": {
            "type": "object",
            "properties": {
                "interval": {
                    "$ref": "#/definitions/biz.AlertInterval"
                },
                "notify_rules": {
                    "type": "array",
                    "items": {
                        "$ref": "#/definitions/biz.NotifyRule"
                    }
                }
            }
        },
        "biz.NotifyRule": {
            "type": "object",
            "properties": {
                "alert_contacts": {
                    "description": "Deprecated: use AlertObjects instead",
                    "type": "array",
                    "items": {
                        "$ref": "#/definitions/biz.AlertContact"
                    }
                },
                "alert_objects": {
                    "type": "array",
                    "items": {
                        "$ref": "#/definitions/biz.AlertContact"
                    }
                },
                "type": {
                    "type": "string"
                }
            }
        },
        "biz.SilenceRule": {
            "type": "object",
            "properties": {
                "enabled": {
                    "description": "true表示静默",
                    "type": "boolean"
                },
                "resume_at": {
                    "type": "string"
                }
            }
        },
        "biz.UpdateAlertRequest": {
            "type": "object",
            "required": [
                "alert_id"
            ],
            "properties": {
                "alert_id": {
                    "type": "string"
                },
                "args": {
                    "type": "array",
                    "items": {
                        "$ref": "#/definitions/biz.ArgsUnit"
                    }
                },
                "level": {
                    "type": "string"
                },
                "receivers": {
                    "type": "array",
                    "items": {
                        "type": "string"
                    }
                },
                "repeat_interval": {
                    "type": "integer"
                },
                "silence_rule": {
                    "$ref": "#/definitions/biz.SilenceRule"
                }
            }
        },
        "biz.UpdateAlertResponse": {
            "type": "object"
        },
        "errno.Result": {
            "type": "object",
            "properties": {
                "code": {
                    "description": "error code",
                    "type": "string"
                },
                "data": {
                    "description": "data returned on success"
                },
                "msg": {
                    "description": "error description",
                    "type": "string"
                },
                "request_id": {
                    "description": "unique RequestID of the current request",
                    "type": "string"
                }
            }
        },
        "internal_service.ListAlertDefaultInfoRequest": {
            "type": "object"
        },
        "internal_service.ListAlertDefaultInfoResponse": {
            "type": "object",
            "properties": {
                "alert_default_infos": {
                    "type": "array",
                    "items": {
                        "$ref": "#/definitions/biz.AlertDefaultInfo"
                    }
                }
            }
        }
    }
}